{
  "@context": "https://schema.org",
  "@type": [
    "Place",
    "ItemList",
    "Product"
  ],
  "numberOfItems": 112586,
  "url": "https://www.bayut.com/for-sale/property/dubai/page-963/",
  "name": "Dubai",
  "geo": {
    "@type": "GeoCoordinates",
    "latitude": 25.024769324449,
    "longitude": 55.359007938377
  },
  "itemListElement": [
    {
      "@type": "ItemPage",
      "url": "https://www.bayut.com/property/details-12678933.html",
      "mainEntity": {
        "@type": [
          "Product",
          "Apartment"
        ],
        "name": "Selling at OP |Mid Floor |Villas and Lagoon Views",
        "url": "https://www.bayut.com/property/details-12678933.html",
        "geo": {
          "@type": "GeoCoordinates",
          "latitude": 25.103700025383,
          "longitude": 55.244314518826
        },
        "floorSize": {
          "@type": "QuantitativeValue",
          "value": "747",
          "unitText": "SQFT"
        },
        "numberOfRooms": {
          "@type": "QuantitativeValue",
          "name": "Bedroom(s)",
          "value": "1"
        },
        "numberOfBathroomsTotal": "1",
        "image": "https://images.bayut.com/thumbnails/792519517-400x300.jpeg",
        "address": {
          "@type": "PostalAddress",
          "addressRegion": "Dubai",
          "addressLocality": "Dubai Hills Estate"
        },
        "offers": [
          {
            "@type": "Offer",
            "priceCurrency": "AED",
            "url": "https://www.bayut.com/property/details-12678933.html",
            "priceSpecification": {
              "@type": "UnitPriceSpecification",
              "price": 1790000,
              "priceCurrency": "AED"
            }
          }
        ]
      },
      "position": 1
    },
    {
      "@type": "ItemPage",
      "url": "https://www.bayut.com/property/details-12677467.html",
      "mainEntity": {
        "@type": [
          "Product",
          "Apartment"
        ],
        "name": "Flexible Payment Plan|Luxury| High ROI | Prime Location",
        "url": "https://www.bayut.com/property/details-12677467.html",
        "geo": {
          "@type": "GeoCoordinates",
          "latitude": 25.097561066257,
          "longitude": 55.372276929702
        },
        "floorSize": {
          "@type": "QuantitativeValue",
          "value": "1,083",
          "unitText": "SQFT"
        },
        "numberOfRooms": {
          "@type": "QuantitativeValue",
          "name": "Bedroom(s)",
          "value": "2"
        },
        "numberOfBathroomsTotal": "3",
        "image": "https://images.bayut.com/thumbnails/792502468-400x300.jpeg",
        "address": {
          "@type": "PostalAddress",
          "addressRegion": "Dubai",
          "addressLocality": "Dubai Land Residence Complex"
        },
        "offers": [
          {
            "@type": "Offer",
            "priceCurrency": "AED",
            "url": "https://www.bayut.com/property/details-12677467.html",
            "priceSpecification": {
              "@type": "UnitPriceSpecification",
              "price": 1732229,
              "priceCurrency": "AED"
            }
          }
        ]
      },
      "position": 2
    },
    {
      "@type": "ItemPage",
      "url": "https://www.bayut.com/property/details-12676910.html",
      "mainEntity": {
        "@type": [
          "Product",
          "Apartment"
        ],
        "name": "Investor Deal | Prime Location | Flexible Payment Plan",
        "url": "https://www.bayut.com/property/details-12676910.html",
        "geo": {
          "@type": "GeoCoordinates",
          "latitude": 25.049826148537,
          "longitude": 55.241376705462
        },
        "floorSize": {
          "@type": "QuantitativeValue",
          "value": "1,895",
          "unitText": "SQFT"
        },
        "numberOfRooms": {
          "@type": "QuantitativeValue",
          "name": "Bedroom(s)",
          "value": "3"
        },
        "numberOfBathroomsTotal": "4",
        "image": "https://images.bayut.com/thumbnails/792494532-400x300.jpeg",
        "address": {
          "@type": "PostalAddress",
          "addressRegion": "Dubai",
          "addressLocality": "Motor City"
        },
        "offers": [
          {
            "@type": "Offer",
            "priceCurrency": "AED",
            "url": "https://www.bayut.com/property/details-12676910.html",
            "priceSpecification": {
              "@type": "UnitPriceSpecification",
              "price": 3951492,
              "priceCurrency": "AED"
            }
          }
        ]
      },
      "position": 3
    },
    {
      "@type": "ItemPage",
      "url": "https://www.bayut.com/property/details-12673038.html",
      "mainEntity": {
        "@type": [
          "Product",
          "Apartment"
        ],
        "name": "High Floor | Pool and Park View | Multiple Options",
        "url": "https://www.bayut.com/property/details-12673038.html",
        "geo": {
          "@type": "GeoCoordinates",
          "latitude": 25.106380094527,
          "longitude": 55.241824929594
        },
        "floorSize": {
          "@type": "QuantitativeValue",
          "value": "704",
          "unitText": "SQFT"
        },
        "numberOfRooms": {
          "@type": "QuantitativeValue",
          "name": "Bedroom(s)",
          "value": "1"
        },
        "numberOfBathroomsTotal": "1",
        "image": "https://images.bayut.com/thumbnails/792433887-400x300.jpeg",
        "address": {
          "@type": "PostalAddress",
          "addressRegion": "Dubai",
          "addressLocality": "Dubai Hills Estate"
        },
        "offers": [
          {
            "@type": "Offer",
            "priceCurrency": "AED",
            "url": "https://www.bayut.com/property/details-12673038.html",
            "priceSpecification": {
              "@type": "UnitPriceSpecification",
              "price": 1800000,
              "priceCurrency": "AED"
            }
          }
        ]
      },
      "position": 4
    },
    {
      "@type": "ItemPage",
      "url": "https://www.bayut.com/property/details-12672546.html",
      "mainEntity": {
        "@type": [
          "Product",
          "House"
        ],
        "name": "Luxury 3 BHK I Phase 4 I Great Location",
        "url": "https://www.bayut.com/property/details-12672546.html",
        "geo": {
          "@type": "GeoCoordinates",
          "latitude": 25.13498063597,
          "longitude": 55.309123986899
        },
        "floorSize": {
          "@type": "QuantitativeValue",
          "value": "1,959",
          "unitText": "SQFT"
        },
        "numberOfRooms": {
          "@type": "QuantitativeValue",
          "name": "Bedroom(s)",
          "value": "3"
        },
        "numberOfBathroomsTotal": "4",
        "image": "https://images.bayut.com/thumbnails/792423472-400x300.jpeg",
        "address": {
          "@type": "PostalAddress",
          "addressRegion": "Dubai",
          "addressLocality": "Nad Al Sheba"
        },
        "offers": [
          {
            "@type": "Offer",
            "priceCurrency": "AED",
            "url": "https://www.bayut.com/property/details-12672546.html",
            "priceSpecification": {
              "@type": "UnitPriceSpecification",
              "price": 5100000,
              "priceCurrency": "AED"
            }
          }
        ]
      },
      "position": 5
    },
    {
      "@type": "ItemPage",
      "url": "https://www.bayut.com/property/details-12667821.html",
      "mainEntity": {
        "@type": [
          "Product",
          "Residence"
        ],
        "name": "40% Off Discount | Flexible Payment Plan Options | Premium Location",
        "url": "https://www.bayut.com/property/details-12667821.html",
        "geo": {
          "@type": "GeoCoordinates",
          "latitude": 25.01950829276,
          "longitude": 55.236063573878
        },
        "floorSize": {
          "@type": "QuantitativeValue",
          "value": "1,960",
          "unitText": "SQFT"
        },
        "numberOfRooms": {
          "@type": "QuantitativeValue",
          "name": "Bedroom(s)",
          "value": "3"
        },
        "numberOfBathroomsTotal": "4",
        "image": "https://images.bayut.com/thumbnails/792362638-400x300.jpeg",
        "address": {
          "@type": "PostalAddress",
          "addressRegion": "Dubai",
          "addressLocality": "Dubailand"
        },
        "offers": [
          {
            "@type": "Offer",
            "priceCurrency": "AED",
            "url": "https://www.bayut.com/property/details-12667821.html",
            "priceSpecification": {
              "@type": "UnitPriceSpecification",
              "price": 1557000,
              "priceCurrency": "AED"
            }
          }
        ]
      },
      "position": 6
    },
    {
      "@type": "ItemPage",
      "url": "https://www.bayut.com/property/details-12664970.html",
      "mainEntity": {
        "@type": [
          "Product",
          "House"
        ],
        "name": "5 Beds Plus Maids Room | High ROI | Modern Living",
        "url": "https://www.bayut.com/property/details-12664970.html",
        "geo": {
          "@type": "GeoCoordinates",
          "latitude": 24.964584335951,
          "longitude": 55.166035971571
        },
        "floorSize": {
          "@type": "QuantitativeValue",
          "value": "3,953",
          "unitText": "SQFT"
        },
        "numberOfRooms": {
          "@type": "QuantitativeValue",
          "name": "Bedroom(s)",
          "value": "5"
        },
        "numberOfBathroomsTotal": "6",
        "image": "https://images.bayut.com/thumbnails/792306255-400x300.jpeg",
        "address": {
          "@type": "PostalAddress",
          "addressRegion": "Dubai",
          "addressLocality": "Expo City"
        },
        "offers": [
          {
            "@type": "Offer",
            "priceCurrency": "AED",
            "url": "https://www.bayut.com/property/details-12664970.html",
            "priceSpecification": {
              "@type": "UnitPriceSpecification",
              "price": 8200000,
              "priceCurrency": "AED"
            }
          }
        ]
      },
      "position": 7
    },
    {
      "@type": "ItemPage",
      "url": "https://www.bayut.com/property/details-12664922.html",
      "mainEntity": {
        "@type": [
          "Product",
          "House"
        ],
        "name": "High-End Finish | Rooftop Lounge| Smart Investment",
        "url": "https://www.bayut.com/property/details-12664922.html",
        "geo": {
          "@type": "GeoCoordinates",
          "latitude": 24.964584335951,
          "longitude": 55.166035971571
        },
        "floorSize": {
          "@type": "QuantitativeValue",
          "value": "4,219",
          "unitText": "SQFT"
        },
        "numberOfRooms": {
          "@type": "QuantitativeValue",
          "name": "Bedroom(s)",
          "value": "5"
        },
        "numberOfBathroomsTotal": "6",
        "image": "https://images.bayut.com/thumbnails/792305188-400x300.jpeg",
        "address": {
          "@type": "PostalAddress",
          "addressRegion": "Dubai",
          "addressLocality": "Expo City"
        },
        "offers": [
          {
            "@type": "Offer",
            "priceCurrency": "AED",
            "url": "https://www.bayut.com/property/details-12664922.html",
            "priceSpecification": {
              "@type": "UnitPriceSpecification",
              "price": 8412320,
              "priceCurrency": "AED"
            }
          }
        ]
      },
      "position": 8
    },
    {
      "@type": "ItemPage",
      "url": "https://www.bayut.com/property/details-12662560.html",
      "mainEntity": {
        "@type": [
          "Product",
          "Apartment"
        ],
        "name": "Flexible payment plan | High-End Finished | Affordable Prices",
        "url": "https://www.bayut.com/property/details-12662560.html",
        "geo": {
          "@type": "GeoCoordinates",
          "latitude": 25.092510239458,
          "longitude": 55.382364457133
        },
        "floorSize": {
          "@type": "QuantitativeValue",
          "value": "466",
          "unitText": "SQFT"
        },
        "numberOfRooms": {
          "@type": "QuantitativeValue",
          "name": "Bedroom(s)",
          "value": "0"
        },
        "numberOfBathroomsTotal": "1",
        "image": "https://images.bayut.com/thumbnails/792260526-400x300.jpeg",
        "address": {
          "@type": "PostalAddress",
          "addressRegion": "Dubai",
          "addressLocality": "Dubai Land Residence Complex"
        },
        "offers": [
          {
            "@type": "Offer",
            "priceCurrency": "AED",
            "url": "https://www.bayut.com/property/details-12662560.html",
            "priceSpecification": {
              "@type": "UnitPriceSpecification",
              "price": 732000,
              "priceCurrency": "AED"
            }
          }
        ]
      },
      "position": 9
    },
    {
      "@type": "ItemPage",
      "url": "https://www.bayut.com/property/details-12660541.html",
      "mainEntity": {
        "@type": [
          "Product",
          "Apartment"
        ],
        "name": "Spacious Luxury Apartment | High ROI | Waterfront Living | 0% Commission | Cash Price",
        "url": "https://www.bayut.com/property/details-12660541.html",
        "geo": {
          "@type": "GeoCoordinates",
          "latitude": 25.183742835903,
          "longitude": 55.263645360942
        },
        "floorSize": {
          "@type": "QuantitativeValue",
          "value": "1,549",
          "unitText": "SQFT"
        },
        "numberOfRooms": {
          "@type": "QuantitativeValue",
          "name": "Bedroom(s)",
          "value": "2"
        },
        "numberOfBathroomsTotal": "3",
        "image": "https://images.bayut.com/thumbnails/792224855-400x300.jpeg",
        "address": {
          "@type": "PostalAddress",
          "addressRegion": "Dubai",
          "addressLocality": "Business Bay"
        },
        "offers": [
          {
            "@type": "Offer",
            "priceCurrency": "AED",
            "url": "https://www.bayut.com/property/details-12660541.html",
            "priceSpecification": {
              "@type": "UnitPriceSpecification",
              "price": 3500000,
              "priceCurrency": "AED"
            }
          }
        ]
      },
      "position": 10
    },
    {
      "@type": "ItemPage",
      "url": "https://www.bayut.com/property/details-12660257.html",
      "mainEntity": {
        "@type": [
          "Product",
          "Apartment"
        ],
        "name": "Stunning View | Pool Deck | Premium",
        "url": "https://www.bayut.com/property/details-12660257.html",
        "geo": {
          "@type": "GeoCoordinates",
          "latitude": 25.093585094856,
          "longitude": 55.373679490651
        },
        "floorSize": {
          "@type": "QuantitativeValue",
          "value": "1,539",
          "unitText": "SQFT"
        },
        "numberOfRooms": {
          "@type": "QuantitativeValue",
          "name": "Bedroom(s)",
          "value": "2"
        },
        "numberOfBathroomsTotal": "2",
        "image": "https://images.bayut.com/thumbnails/792220947-400x300.jpeg",
        "address": {
          "@type": "PostalAddress",
          "addressRegion": "Dubai",
          "addressLocality": "Dubai Land Residence Complex"
        },
        "offers": [
          {
            "@type": "Offer",
            "priceCurrency": "AED",
            "url": "https://www.bayut.com/property/details-12660257.html",
            "priceSpecification": {
              "@type": "UnitPriceSpecification",
              "price": 1699000,
              "priceCurrency": "AED"
            }
          }
        ]
      },
      "position": 11
    },
    {
      "@type": "ItemPage",
      "url": "https://www.bayut.com/property/details-12660256.html",
      "mainEntity": {
        "@type": [
          "Product",
          "Apartment"
        ],
        "name": "Good Deal | Private Pool | 2BR",
        "url": "https://www.bayut.com/property/details-12660256.html",
        "geo": {
          "@type": "GeoCoordinates",
          "latitude": 25.093585094856,
          "longitude": 55.373679490651
        },
        "floorSize": {
          "@type": "QuantitativeValue",
          "value": "1,464",
          "unitText": "SQFT"
        },
        "numberOfRooms": {
          "@type": "QuantitativeValue",
          "name": "Bedroom(s)",
          "value": "2"
        },
        "numberOfBathroomsTotal": "2",
        "image": "https://images.bayut.com/thumbnails/792220941-400x300.jpeg",
        "address": {
          "@type": "PostalAddress",
          "addressRegion": "Dubai",
          "addressLocality": "Dubai Land Residence Complex"
        },
        "offers": [
          {
            "@type": "Offer",
            "priceCurrency": "AED",
            "url": "https://www.bayut.com/property/details-12660256.html",
            "priceSpecification": {
              "@type": "UnitPriceSpecification",
              "price": 1684000,
              "priceCurrency": "AED"
            }
          }
        ]
      },
      "position": 12
    },
    {
      "@type": "ItemPage",
      "url": "https://www.bayut.com/property/details-12660032.html",
      "mainEntity": {
        "@type": [
          "Product",
          "Apartment"
        ],
        "name": "Post-handover PP | 4% DLD Waiver | Lagoon View",
        "url": "https://www.bayut.com/property/details-12660032.html",
        "geo": {
          "@type": "GeoCoordinates",
          "latitude": 25.181179781717,
          "longitude": 55.326701261904
        },
        "floorSize": {
          "@type": "QuantitativeValue",
          "value": "808",
          "unitText": "SQFT"
        },
        "numberOfRooms": {
          "@type": "QuantitativeValue",
          "name": "Bedroom(s)",
          "value": "1"
        },
        "numberOfBathroomsTotal": "2",
        "image": "https://images.bayut.com/thumbnails/792217984-400x300.jpeg",
        "address": {
          "@type": "PostalAddress",
          "addressRegion": "Dubai",
          "addressLocality": "Bukadra"
        },
        "offers": [
          {
            "@type": "Offer",
            "priceCurrency": "AED",
            "url": "https://www.bayut.com/property/details-12660032.html",
            "priceSpecification": {
              "@type": "UnitPriceSpecification",
              "price": 1739645,
              "priceCurrency": "AED"
            }
          }
        ]
      },
      "position": 13
    },
    {
      "@type": "ItemPage",
      "url": "https://www.bayut.com/property/details-12659861.html",
      "mainEntity": {
        "@type": [
          "Product",
          "Apartment"
        ],
        "name": "Marina Views | Motivated Seller | Fully Paid",
        "url": "https://www.bayut.com/property/details-12659861.html",
        "geo": {
          "@type": "GeoCoordinates",
          "latitude": 25.074560549404,
          "longitude": 55.139365038694
        },
        "floorSize": {
          "@type": "QuantitativeValue",
          "value": "603",
          "unitText": "SQFT"
        },
        "numberOfRooms": {
          "@type": "QuantitativeValue",
          "name": "Bedroom(s)",
          "value": "1"
        },
        "numberOfBathroomsTotal": "1",
        "image": "https://images.bayut.com/thumbnails/792215712-400x300.jpeg",
        "address": {
          "@type": "PostalAddress",
          "addressRegion": "Dubai",
          "addressLocality": "Dubai Marina"
        },
        "offers": [
          {
            "@type": "Offer",
            "priceCurrency": "AED",
            "url": "https://www.bayut.com/property/details-12659861.html",
            "priceSpecification": {
              "@type": "UnitPriceSpecification",
              "price": 2235000,
              "priceCurrency": "AED"
            }
          }
        ]
      },
      "position": 14
    },
    {
      "@type": "ItemPage",
      "url": "https://www.bayut.com/property/details-12659524.html",
      "mainEntity": {
        "@type": [
          "Product",
          "Apartment"
        ],
        "name": "2BR | Private Pool | Great Deal",
        "url": "https://www.bayut.com/property/details-12659524.html",
        "geo": {
          "@type": "GeoCoordinates",
          "latitude": 25.093585094856,
          "longitude": 55.373679490651
        },
        "floorSize": {
          "@type": "QuantitativeValue",
          "value": "1,464",
          "unitText": "SQFT"
        },
        "numberOfRooms": {
          "@type": "QuantitativeValue",
          "name": "Bedroom(s)",
          "value": "2"
        },
        "numberOfBathroomsTotal": "2",
        "image": "https://images.bayut.com/thumbnails/792210879-400x300.jpeg",
        "address": {
          "@type": "PostalAddress",
          "addressRegion": "Dubai",
          "addressLocality": "Dubai Land Residence Complex"
        },
        "offers": [
          {
            "@type": "Offer",
            "priceCurrency": "AED",
            "url": "https://www.bayut.com/property/details-12659524.html",
            "priceSpecification": {
              "@type": "UnitPriceSpecification",
              "price": 1654000,
              "priceCurrency": "AED"
            }
          }
        ]
      },
      "position": 15
    },
    {
      "@type": "ItemPage",
      "url": "https://www.bayut.com/property/details-12659351.html",
      "mainEntity": {
        "@type": [
          "Product",
          "Apartment"
        ],
        "name": "Cash Offer / Prime Location / Near Handover / No Commission",
        "url": "https://www.bayut.com/property/details-12659351.html",
        "geo": {
          "@type": "GeoCoordinates",
          "latitude": 25.043675355416,
          "longitude": 55.218749385907
        },
        "floorSize": {
          "@type": "QuantitativeValue",
          "value": "1,138",
          "unitText": "SQFT"
        },
        "numberOfRooms": {
          "@type": "QuantitativeValue",
          "name": "Bedroom(s)",
          "value": "2"
        },
        "numberOfBathroomsTotal": "3",
        "image": "https://images.bayut.com/thumbnails/792208050-400x300.jpeg",
        "address": {
          "@type": "PostalAddress",
          "addressRegion": "Dubai",
          "addressLocality": "Dubai Sports City"
        },
        "offers": [
          {
            "@type": "Offer",
            "priceCurrency": "AED",
            "url": "https://www.bayut.com/property/details-12659351.html",
            "priceSpecification": {
              "@type": "UnitPriceSpecification",
              "price": 1597999,
              "priceCurrency": "AED"
            }
          }
        ]
      },
      "position": 16
    },
    {
      "@type": "ItemPage",
      "url": "https://www.bayut.com/property/details-12659103.html",
      "mainEntity": {
        "@type": [
          "Product",
          "Apartment"
        ],
        "name": "2-Bedroom Modern Living | Pool & Stadium Views | Active Lifestyle Community",
        "url": "https://www.bayut.com/property/details-12659103.html",
        "geo": {
          "@type": "GeoCoordinates",
          "latitude": 25.042772879265,
          "longitude": 55.216950955278
        },
        "floorSize": {
          "@type": "QuantitativeValue",
          "value": "1,242",
          "unitText": "SQFT"
        },
        "numberOfRooms": {
          "@type": "QuantitativeValue",
          "name": "Bedroom(s)",
          "value": "2"
        },
        "numberOfBathroomsTotal": "2",
        "image": "https://images.bayut.com/thumbnails/792204675-400x300.jpeg",
        "address": {
          "@type": "PostalAddress",
          "addressRegion": "Dubai",
          "addressLocality": "Dubai Sports City"
        },
        "offers": [
          {
            "@type": "Offer",
            "priceCurrency": "AED",
            "url": "https://www.bayut.com/property/details-12659103.html",
            "priceSpecification": {
              "@type": "UnitPriceSpecification",
              "price": 1609999,
              "priceCurrency": "AED"
            }
          }
        ]
      },
      "position": 17
    },
    {
      "@type": "ItemPage",
      "url": "https://www.bayut.com/property/details-12657346.html",
      "mainEntity": {
        "@type": [
          "Product",
          "Apartment"
        ],
        "name": "Top Location | Smart Features | Best Price",
        "url": "https://www.bayut.com/property/details-12657346.html",
        "geo": {
          "@type": "GeoCoordinates",
          "latitude": 25.094778,
          "longitude": 55.375278
        },
        "floorSize": {
          "@type": "QuantitativeValue",
          "value": "729",
          "unitText": "SQFT"
        },
        "numberOfRooms": {
          "@type": "QuantitativeValue",
          "name": "Bedroom(s)",
          "value": "1"
        },
        "numberOfBathroomsTotal": "1",
        "image": "https://images.bayut.com/thumbnails/792177699-400x300.jpeg",
        "address": {
          "@type": "PostalAddress",
          "addressRegion": "Dubai",
          "addressLocality": "Dubai Land Residence Complex"
        },
        "offers": [
          {
            "@type": "Offer",
            "priceCurrency": "AED",
            "url": "https://www.bayut.com/property/details-12657346.html",
            "priceSpecification": {
              "@type": "UnitPriceSpecification",
              "price": 965359,
              "priceCurrency": "AED"
            }
          }
        ]
      },
      "position": 18
    },
    {
      "@type": "ItemPage",
      "url": "https://www.bayut.com/property/details-12657177.html",
      "mainEntity": {
        "@type": [
          "Product",
          "Apartment"
        ],
        "name": "Elegant Layout | Flexible PHPP | Mid Floor",
        "url": "https://www.bayut.com/property/details-12657177.html",
        "geo": {
          "@type": "GeoCoordinates",
          "latitude": 25.095326323744,
          "longitude": 55.372287816845
        },
        "floorSize": {
          "@type": "QuantitativeValue",
          "value": "465",
          "unitText": "SQFT"
        },
        "numberOfRooms": {
          "@type": "QuantitativeValue",
          "name": "Bedroom(s)",
          "value": "0"
        },
        "numberOfBathroomsTotal": "1",
        "image": "https://images.bayut.com/thumbnails/792174725-400x300.jpeg",
        "address": {
          "@type": "PostalAddress",
          "addressRegion": "Dubai",
          "addressLocality": "Dubai Land Residence Complex"
        },
        "offers": [
          {
            "@type": "Offer",
            "priceCurrency": "AED",
            "url": "https://www.bayut.com/property/details-12657177.html",
            "priceSpecification": {
              "@type": "UnitPriceSpecification",
              "price": 695000,
              "priceCurrency": "AED"
            }
          }
        ]
      },
      "position": 19
    },
    {
      "@type": "ItemPage",
      "url": "https://www.bayut.com/property/details-12656949.html",
      "mainEntity": {
        "@type": [
          "Product",
          "Apartment"
        ],
        "name": "Dubai Hills| GOLF COURSE | HIGH ROI | LAYOUT | ROI | 10% Down Payment",
        "url": "https://www.bayut.com/property/details-12656949.html",
        "geo": {
          "@type": "GeoCoordinates",
          "latitude": 25.129889,
          "longitude": 55.262778
        },
        "floorSize": {
          "@type": "QuantitativeValue",
          "value": "745",
          "unitText": "SQFT"
        },
        "numberOfRooms": {
          "@type": "QuantitativeValue",
          "name": "Bedroom(s)",
          "value": "1"
        },
        "numberOfBathroomsTotal": "2",
        "image": "https://images.bayut.com/thumbnails/792240950-400x300.jpeg",
        "address": {
          "@type": "PostalAddress",
          "addressRegion": "Dubai",
          "addressLocality": "Dubai Hills Estate"
        },
        "offers": [
          {
            "@type": "Offer",
            "priceCurrency": "AED",
            "url": "https://www.bayut.com/property/details-12656949.html",
            "priceSpecification": {
              "@type": "UnitPriceSpecification",
              "price": 1615888,
              "priceCurrency": "AED"
            }
          }
        ]
      },
      "position": 20
    },
    {
      "@type": "ItemPage",
      "url": "https://www.bayut.com/property/details-12654316.html",
      "mainEntity": {
        "@type": [
          "Product",
          "Apartment"
        ],
        "name": "Spacious Design | Quiet Streets | Family Comfort",
        "url": "https://www.bayut.com/property/details-12654316.html",
        "geo": {
          "@type": "GeoCoordinates",
          "latitude": 25.018394661921,
          "longitude": 55.121535097506
        },
        "floorSize": {
          "@type": "QuantitativeValue",
          "value": "1,160",
          "unitText": "SQFT"
        },
        "numberOfRooms": {
          "@type": "QuantitativeValue",
          "name": "Bedroom(s)",
          "value": "2"
        },
        "numberOfBathroomsTotal": "3",
        "image": "https://images.bayut.com/thumbnails/792066715-400x300.jpeg",
        "address": {
          "@type": "PostalAddress",
          "addressRegion": "Dubai",
          "addressLocality": "Al Furjan"
        },
        "offers": [
          {
            "@type": "Offer",
            "priceCurrency": "AED",
            "url": "https://www.bayut.com/property/details-12654316.html",
            "priceSpecification": {
              "@type": "UnitPriceSpecification",
              "price": 1891000,
              "priceCurrency": "AED"
            }
          }
        ]
      },
      "position": 21
    },
    {
      "@type": "ItemPage",
      "url": "https://www.bayut.com/property/details-12654309.html",
      "mainEntity": {
        "@type": [
          "Product",
          "Apartment"
        ],
        "name": "Comfort Living | Secure Area | Growing Community",
        "url": "https://www.bayut.com/property/details-12654309.html",
        "geo": {
          "@type": "GeoCoordinates",
          "latitude": 25.018394661921,
          "longitude": 55.121535097506
        },
        "floorSize": {
          "@type": "QuantitativeValue",
          "value": "1,160",
          "unitText": "SQFT"
        },
        "numberOfRooms": {
          "@type": "QuantitativeValue",
          "name": "Bedroom(s)",
          "value": "2"
        },
        "numberOfBathroomsTotal": "3",
        "image": "https://images.bayut.com/thumbnails/792066678-400x300.jpeg",
        "address": {
          "@type": "PostalAddress",
          "addressRegion": "Dubai",
          "addressLocality": "Al Furjan"
        },
        "offers": [
          {
            "@type": "Offer",
            "priceCurrency": "AED",
            "url": "https://www.bayut.com/property/details-12654309.html",
            "priceSpecification": {
              "@type": "UnitPriceSpecification",
              "price": 1894000,
              "priceCurrency": "AED"
            }
          }
        ]
      },
      "position": 22
    },
    {
      "@type": "ItemPage",
      "url": "https://www.bayut.com/property/details-12652740.html",
      "mainEntity": {
        "@type": [
          "Product",
          "Apartment"
        ],
        "name": "Near Metro |Investor Deal | Prime Location |High ROI",
        "url": "https://www.bayut.com/property/details-12652740.html",
        "geo": {
          "@type": "GeoCoordinates",
          "latitude": 25.020758150367,
          "longitude": 55.106726226244
        },
        "floorSize": {
          "@type": "QuantitativeValue",
          "value": "726",
          "unitText": "SQFT"
        },
        "numberOfRooms": {
          "@type": "QuantitativeValue",
          "name": "Bedroom(s)",
          "value": "1"
        },
        "numberOfBathroomsTotal": "2",
        "image": "https://images.bayut.com/thumbnails/792038098-400x300.jpeg",
        "address": {
          "@type": "PostalAddress",
          "addressRegion": "Dubai",
          "addressLocality": "Wasl Gate"
        },
        "offers": [
          {
            "@type": "Offer",
            "priceCurrency": "AED",
            "url": "https://www.bayut.com/property/details-12652740.html",
            "priceSpecification": {
              "@type": "UnitPriceSpecification",
              "price": 1141000,
              "priceCurrency": "AED"
            }
          }
        ]
      },
      "position": 23
    },
    {
      "@type": "ItemPage",
      "url": "https://www.bayut.com/property/details-12652696.html",
      "mainEntity": {
        "@type": [
          "Product",
          "Apartment"
        ],
        "name": "Refined Living| Modern Layouts | Stylish 2 Bedroom",
        "url": "https://www.bayut.com/property/details-12652696.html",
        "geo": {
          "@type": "GeoCoordinates",
          "latitude": 24.943904207036,
          "longitude": 55.21921813577
        },
        "floorSize": {
          "@type": "QuantitativeValue",
          "value": "983",
          "unitText": "SQFT"
        },
        "numberOfRooms": {
          "@type": "QuantitativeValue",
          "name": "Bedroom(s)",
          "value": "2"
        },
        "numberOfBathroomsTotal": "2",
        "image": "https://images.bayut.com/thumbnails/792038170-400x300.jpeg",
        "address": {
          "@type": "PostalAddress",
          "addressRegion": "Dubai",
          "addressLocality": "Dubai South"
        },
        "offers": [
          {
            "@type": "Offer",
            "priceCurrency": "AED",
            "url": "https://www.bayut.com/property/details-12652696.html",
            "priceSpecification": {
              "@type": "UnitPriceSpecification",
              "price": 1292000,
              "priceCurrency": "AED"
            }
          }
        ]
      },
      "position": 24
    }
  ],
  "offers": {
    "@type": "AggregateOffer",
    "url": "https://www.bayut.com/for-sale/property/dubai/page-963/",
    "lowPrice": 498000,
    "highPrice": 41000000,
    "offerCount": 112586,
    "priceCurrency": "AED"
  }
}